{"msg": "查询成功!", "code": 200, "data": [{"endPointTime": "00:15", "record1": 328.93, "record2": 303.63}, {"endPointTime": "00:30", "record1": 331.08, "record2": 325.3}, {"endPointTime": "00:45", "record1": 327.2, "record2": 315.8}, {"endPointTime": "01:00", "record1": 323.32, "record2": 308.97}, {"endPointTime": "01:15", "record1": 322.19, "record2": 303.79}, {"endPointTime": "01:30", "record1": 320.68, "record2": 306.23}, {"endPointTime": "01:45", "record1": 320.14, "record2": 291.64}, {"endPointTime": "02:00", "record1": 319.75, "record2": 285.77}, {"endPointTime": "02:15", "record1": 319.73, "record2": 290.62}, {"endPointTime": "02:30", "record1": 316.89, "record2": 277.85}, {"endPointTime": "02:45", "record1": 317.12, "record2": 278.99}, {"endPointTime": "03:00", "record1": 317.65, "record2": 274.92}, {"endPointTime": "03:15", "record1": 315.61, "record2": 273.8}, {"endPointTime": "03:30", "record1": 314.31, "record2": 272.91}, {"endPointTime": "03:45", "record1": 316.14, "record2": 277.51}, {"endPointTime": "04:00", "record1": 316.11, "record2": 275.22}, {"endPointTime": "04:15", "record1": 316.77, "record2": 272.62}, {"endPointTime": "04:30", "record1": 317.86, "record2": 262.85}, {"endPointTime": "04:45", "record1": 316.36, "record2": 282.3}, {"endPointTime": "05:00", "record1": 316.45, "record2": 285.89}, {"endPointTime": "05:15", "record1": 324.08, "record2": 297.35}, {"endPointTime": "05:30", "record1": 330.53, "record2": 304.36}, {"endPointTime": "05:45", "record1": 336.61, "record2": 323.46}, {"endPointTime": "06:00", "record1": 339.44, "record2": 343.43}, {"endPointTime": "06:15", "record1": 356.52, "record2": 369.18}, {"endPointTime": "06:30", "record1": 361.28, "record2": 367.8}, {"endPointTime": "06:45", "record1": 363.86, "record2": 378.96}, {"endPointTime": "07:00", "record1": 362.25, "record2": 376.06}, {"endPointTime": "07:15", "record1": 361.34, "record2": 376.15}, {"endPointTime": "07:30", "record1": 351.72, "record2": 351.12}, {"endPointTime": "07:45", "record1": 338.8, "record2": 340.97}, {"endPointTime": "08:00", "record1": 329.04, "record2": 316.4}, {"endPointTime": "08:15", "record1": 316.54, "record2": 328.38}, {"endPointTime": "08:30", "record1": 306.89, "record2": 330.02}, {"endPointTime": "08:45", "record1": 299.45, "record2": 311.3}, {"endPointTime": "09:00", "record1": 287.86, "record2": 307.69}, {"endPointTime": "09:15", "record1": 275.4, "record2": 301.52}, {"endPointTime": "09:30", "record1": 254.94, "record2": 254.08}, {"endPointTime": "09:45", "record1": 244.33, "record2": 232.27}, {"endPointTime": "10:00", "record1": 228.14, "record2": 219.74}, {"endPointTime": "10:15", "record1": 229.85, "record2": 219.41}, {"endPointTime": "10:30", "record1": 214.49, "record2": 195.93}, {"endPointTime": "10:45", "record1": 195.85, "record2": 189.34}, {"endPointTime": "11:00", "record1": 244.27, "record2": 180.7}, {"endPointTime": "11:15", "record1": 239.27, "record2": 172.64}, {"endPointTime": "11:30", "record1": 225.77, "record2": 171.98}, {"endPointTime": "11:45", "record1": 201.94, "record2": 165.91}, {"endPointTime": "12:00", "record1": 157.0, "record2": 121.37}, {"endPointTime": "12:15", "record1": 134.26, "record2": 109.6}, {"endPointTime": "12:30", "record1": 118.04, "record2": 79.94}, {"endPointTime": "12:45", "record1": 97.63, "record2": 97.41}, {"endPointTime": "13:00", "record1": 88.31, "record2": 96.44}, {"endPointTime": "13:15", "record1": 86.11, "record2": 90.71}, {"endPointTime": "13:30", "record1": 85.29, "record2": 80.17}, {"endPointTime": "13:45", "record1": 84.83, "record2": 89.87}, {"endPointTime": "14:00", "record1": 87.5, "record2": 100.17}, {"endPointTime": "14:15", "record1": 111.79, "record2": 110.12}, {"endPointTime": "14:30", "record1": 126.39, "record2": 110.33}, {"endPointTime": "14:45", "record1": 150.43, "record2": 120.35}, {"endPointTime": "15:00", "record1": 176.51, "record2": 127.36}, {"endPointTime": "15:15", "record1": 165.48, "record2": 154.98}, {"endPointTime": "15:30", "record1": 192.04, "record2": 179.8}, {"endPointTime": "15:45", "record1": 211.15, "record2": 190.07}, {"endPointTime": "16:00", "record1": 227.07, "record2": 205.23}, {"endPointTime": "16:15", "record1": 225.24, "record2": 222.99}, {"endPointTime": "16:30", "record1": 258.41, "record2": 284.84}, {"endPointTime": "16:45", "record1": 322.73, "record2": 320.82}, {"endPointTime": "17:00", "record1": 351.69, "record2": 367.7}, {"endPointTime": "17:15", "record1": 357.58, "record2": 369.78}, {"endPointTime": "17:30", "record1": 376.16, "record2": 407.27}, {"endPointTime": "17:45", "record1": 394.85, "record2": 436.78}, {"endPointTime": "18:00", "record1": 412.63, "record2": 473.16}, {"endPointTime": "18:15", "record1": 422.77, "record2": 508.36}, {"endPointTime": "18:30", "record1": 440.91, "record2": 501.88}, {"endPointTime": "18:45", "record1": 466.14, "record2": 539.48}, {"endPointTime": "19:00", "record1": 500.01, "record2": 575.05}, {"endPointTime": "19:15", "record1": 524.9, "record2": 623.46}, {"endPointTime": "19:30", "record1": 532.47, "record2": 648.2}, {"endPointTime": "19:45", "record1": 498.68, "record2": 589.09}, {"endPointTime": "20:00", "record1": 467.89, "record2": 502.38}, {"endPointTime": "20:15", "record1": 448.35, "record2": 503.33}, {"endPointTime": "20:30", "record1": 435.11, "record2": 468.98}, {"endPointTime": "20:45", "record1": 420.71, "record2": 469.9}, {"endPointTime": "21:00", "record1": 414.99, "record2": 445.64}, {"endPointTime": "21:15", "record1": 416.55, "record2": 451.76}, {"endPointTime": "21:30", "record1": 411.69, "record2": 445.27}, {"endPointTime": "21:45", "record1": 405.82, "record2": 425.48}, {"endPointTime": "22:00", "record1": 397.24, "record2": 416.36}, {"endPointTime": "22:15", "record1": 389.72, "record2": 403.66}, {"endPointTime": "22:30", "record1": 379.96, "record2": 368.71}, {"endPointTime": "22:45", "record1": 367.68, "record2": 348.96}, {"endPointTime": "23:00", "record1": 353.8, "record2": 333.71}, {"endPointTime": "23:15", "record1": 344.02, "record2": 329.61}, {"endPointTime": "23:30", "record1": 338.55, "record2": 327.62}, {"endPointTime": "23:45", "record1": 334.16, "record2": 314.87}, {"endPointTime": "24:00", "record1": 329.13, "record2": 311.77}]}