{"nodes": [{"id": "opencode_command_gsd_settings", "label": "gsd-settings - GSD workflow config", "file_type": "document", "source_file": ".opencode/command/gsd-settings.md", "source_location": null, "source_url": null, "captured_at": null, "author": null, "contributor": null}], "edges": [{"source": "opencode_command_gsd_settings", "target": "opencode_command_gsd", "relation": "member_of", "confidence": "EXTRACTED", "confidence_score": 1.0, "source_file": ".opencode/command/gsd-settings.md", "source_location": null, "weight": 1.0}], "hyperedges": []}