{"nodes": [{"id": "planning_research_stack", "label": "Technology Stack Research", "file_type": "document", "source_file": ".planning/research/STACK.md", "source_location": null, "source_url": null, "captured_at": null, "author": null, "contributor": null}], "edges": [{"source": "planning_research_stack", "target": "planning_project_ellectric", "relation": "recommends_stack_for", "confidence": "EXTRACTED", "confidence_score": 1.0, "source_file": ".planning/research/STACK.md", "source_location": null, "weight": 1.0}], "hyperedges": []}