{"nodes": [{"id": "mnt_e_electric_sillyspec_changes_archive_2026_06_23_2026_06_22_shanxi_spot_data_access_tasks_task_01_md", "label": "task-01.md", "file_type": "document", "source_file": ".sillyspec/changes/archive/2026-06-23-2026-06-22-shanxi-spot-data-access/tasks/task-01.md", "source_location": "L1"}, {"id": "tasks_task_01_task_01_\u5199_data_raw_shanxi_readme_md_\u6570\u636e\u8d44\u4ea7\u8bf4\u660e", "label": "task-01: \u5199 data/raw/shanxi/README.md \u6570\u636e\u8d44\u4ea7\u8bf4\u660e", "file_type": "document", "source_file": ".sillyspec/changes/archive/2026-06-23-2026-06-22-shanxi-spot-data-access/tasks/task-01.md", "source_location": "L15"}, {"id": "tasks_task_01_\u4fee\u6539\u6587\u4ef6_\u5fc5\u586b", "label": "\u4fee\u6539\u6587\u4ef6 (\u5fc5\u586b)", "file_type": "document", "source_file": ".sillyspec/changes/archive/2026-06-23-2026-06-22-shanxi-spot-data-access/tasks/task-01.md", "source_location": "L17"}, {"id": "tasks_task_01_\u8986\u76d6\u6765\u6e90", "label": "\u8986\u76d6\u6765\u6e90", "file_type": "document", "source_file": ".sillyspec/changes/archive/2026-06-23-2026-06-22-shanxi-spot-data-access/tasks/task-01.md", "source_location": "L21"}, {"id": "tasks_task_01_\u5b9e\u73b0\u8981\u6c42", "label": "\u5b9e\u73b0\u8981\u6c42", "file_type": "document", "source_file": ".sillyspec/changes/archive/2026-06-23-2026-06-22-shanxi-spot-data-access/tasks/task-01.md", "source_location": "L26"}, {"id": "tasks_task_01_\u8986\u76d6\u6765\u6e90\u539f\u6587_\u4f9b\u53c2\u8003_execute_\u5b50\u4ee3\u7406\u65e0\u9700\u518d\u7ffb_design_decisions", "label": "\u8986\u76d6\u6765\u6e90\u539f\u6587 (\u4f9b\u53c2\u8003, execute \u5b50\u4ee3\u7406\u65e0\u9700\u518d\u7ffb design/decisions)", "file_type": "document", "source_file": ".sillyspec/changes/archive/2026-06-23-2026-06-22-shanxi-spot-data-access/tasks/task-01.md", "source_location": "L39"}, {"id": "tasks_task_01_\u51b3\u7b56_d_002_v1_record1_record2_\u91cd\u547d\u540d", "label": "\u51b3\u7b56 D-002@v1 (record1/record2 \u91cd\u547d\u540d)", "file_type": "document", "source_file": ".sillyspec/changes/archive/2026-06-23-2026-06-22-shanxi-spot-data-access/tasks/task-01.md", "source_location": "L41"}, {"id": "tasks_task_01_\u51b3\u7b56_d_003_v1_rqrecord_ssrecord_\u91cd\u547d\u540d_load_mw_\u6620\u5c04", "label": "\u51b3\u7b56 D-003@v1 (rqRecord/ssRecord \u91cd\u547d\u540d + load_mw \u6620\u5c04)", "file_type": "document", "source_file": ".sillyspec/changes/archive/2026-06-23-2026-06-22-shanxi-spot-data-access/tasks/task-01.md", "source_location": "L45"}, {"id": "tasks_task_01_\u51b3\u7b56_d_006_v1_\u4ec5_3_api_\u63a5\u5165_\u5176\u4f59\u5f52\u6863", "label": "\u51b3\u7b56 D-006@v1 (\u4ec5 3 API \u63a5\u5165, \u5176\u4f59\u5f52\u6863)", "file_type": "document", "source_file": ".sillyspec/changes/archive/2026-06-23-2026-06-22-shanxi-spot-data-access/tasks/task-01.md", "source_location": "L49"}, {"id": "tasks_task_01_\u63a5\u53e3\u5b9a\u4e49_\u4ee3\u7801\u7c7b\u4efb\u52a1\u5fc5\u586b_task_01_readme_\u7c7b\u586b\u5b57\u6bb5\u8868", "label": "\u63a5\u53e3\u5b9a\u4e49 (\u4ee3\u7801\u7c7b\u4efb\u52a1\u5fc5\u586b, task-01 README \u7c7b\u586b\u5b57\u6bb5\u8868)", "file_type": "document", "source_file": ".sillyspec/changes/archive/2026-06-23-2026-06-22-shanxi-spot-data-access/tasks/task-01.md", "source_location": "L53"}, {"id": "tasks_task_01_\u6587\u6863\u7ed3\u6784_markdown_\u6807\u9898\u5c42\u7ea7", "label": "\u6587\u6863\u7ed3\u6784 (Markdown \u6807\u9898\u5c42\u7ea7)", "file_type": "document", "source_file": ".sillyspec/changes/archive/2026-06-23-2026-06-22-shanxi-spot-data-access/tasks/task-01.md", "source_location": "L55"}, {"id": "tasks_task_01_\u7b2c_2_\u8282_api_\u63a5\u5165\u6e05\u5355\u8868_\u5fc5\u987b\u5b8c\u6574_8_\u884c_11_\u884c\u975e\u6838\u5fc3\u5f52\u6863\u8868", "label": "\u7b2c 2 \u8282: API \u63a5\u5165\u6e05\u5355\u8868 (\u5fc5\u987b\u5b8c\u6574 8 \u884c + 11 \u884c\u975e\u6838\u5fc3\u5f52\u6863\u8868)", "file_type": "document", "source_file": ".sillyspec/changes/archive/2026-06-23-2026-06-22-shanxi-spot-data-access/tasks/task-01.md", "source_location": "L79"}, {"id": "tasks_task_01_\u7b2c_3_\u8282_\u5b57\u6bb5\u6620\u5c04\u8be6\u8868_3_\u5f20\u5b50\u8868", "label": "\u7b2c 3 \u8282: \u5b57\u6bb5\u6620\u5c04\u8be6\u8868 (3 \u5f20\u5b50\u8868)", "file_type": "document", "source_file": ".sillyspec/changes/archive/2026-06-23-2026-06-22-shanxi-spot-data-access/tasks/task-01.md", "source_location": "L94"}, {"id": "tasks_task_01_3_1_spot_da", "label": "3.1 spot_da", "file_type": "document", "source_file": ".sillyspec/changes/archive/2026-06-23-2026-06-22-shanxi-spot-data-access/tasks/task-01.md", "source_location": "L96"}, {"id": "tasks_task_01_3_2_spot_rt", "label": "3.2 spot_rt", "file_type": "document", "source_file": ".sillyspec/changes/archive/2026-06-23-2026-06-22-shanxi-spot-data-access/tasks/task-01.md", "source_location": "L108"}, {"id": "tasks_task_01_3_3_month_settle", "label": "3.3 month_settle", "file_type": "document", "source_file": ".sillyspec/changes/archive/2026-06-23-2026-06-22-shanxi-spot-data-access/tasks/task-01.md", "source_location": "L118"}, {"id": "tasks_task_01_\u8fb9\u754c\u5904\u7406_\u81f3\u5c11_5_\u6761", "label": "\u8fb9\u754c\u5904\u7406 (\u81f3\u5c11 5 \u6761)", "file_type": "document", "source_file": ".sillyspec/changes/archive/2026-06-23-2026-06-22-shanxi-spot-data-access/tasks/task-01.md", "source_location": "L129"}, {"id": "tasks_task_01_\u975e\u76ee\u6807_\u672c\u4efb\u52a1\u4e0d\u505a\u7684\u4e8b", "label": "\u975e\u76ee\u6807 (\u672c\u4efb\u52a1\u4e0d\u505a\u7684\u4e8b)", "file_type": "document", "source_file": ".sillyspec/changes/archive/2026-06-23-2026-06-22-shanxi-spot-data-access/tasks/task-01.md", "source_location": "L139"}, {"id": "tasks_task_01_\u53c2\u8003", "label": "\u53c2\u8003", "file_type": "document", "source_file": ".sillyspec/changes/archive/2026-06-23-2026-06-22-shanxi-spot-data-access/tasks/task-01.md", "source_location": "L149"}, {"id": "tasks_task_01_tdd_\u6b65\u9aa4_\u4ee3\u7801\u7c7b\u4efb\u52a1_\u6587\u6863\u7c7b\u4efb\u52a1\u8df3\u8fc7", "label": "TDD \u6b65\u9aa4 (\u4ee3\u7801\u7c7b\u4efb\u52a1, \u6587\u6863\u7c7b\u4efb\u52a1\u8df3\u8fc7)", "file_type": "document", "source_file": ".sillyspec/changes/archive/2026-06-23-2026-06-22-shanxi-spot-data-access/tasks/task-01.md", "source_location": "L161"}, {"id": "tasks_task_01_\u9a8c\u6536\u6807\u51c6", "label": "\u9a8c\u6536\u6807\u51c6", "file_type": "document", "source_file": ".sillyspec/changes/archive/2026-06-23-2026-06-22-shanxi-spot-data-access/tasks/task-01.md", "source_location": "L173"}], "edges": [{"source": "mnt_e_electric_sillyspec_changes_archive_2026_06_23_2026_06_22_shanxi_spot_data_access_tasks_task_01_md", "target": "tasks_task_01_task_01_\u5199_data_raw_shanxi_readme_md_\u6570\u636e\u8d44\u4ea7\u8bf4\u660e", "relation": "contains", "confidence": "EXTRACTED", "source_file": ".sillyspec/changes/archive/2026-06-23-2026-06-22-shanxi-spot-data-access/tasks/task-01.md", "source_location": "L15", "weight": 1.0}, {"source": "tasks_task_01_task_01_\u5199_data_raw_shanxi_readme_md_\u6570\u636e\u8d44\u4ea7\u8bf4\u660e", "target": "tasks_task_01_\u4fee\u6539\u6587\u4ef6_\u5fc5\u586b", "relation": "contains", "confidence": "EXTRACTED", "source_file": ".sillyspec/changes/archive/2026-06-23-2026-06-22-shanxi-spot-data-access/tasks/task-01.md", "source_location": "L17", "weight": 1.0}, {"source": "tasks_task_01_task_01_\u5199_data_raw_shanxi_readme_md_\u6570\u636e\u8d44\u4ea7\u8bf4\u660e", "target": "tasks_task_01_\u8986\u76d6\u6765\u6e90", "relation": "contains", "confidence": "EXTRACTED", "source_file": ".sillyspec/changes/archive/2026-06-23-2026-06-22-shanxi-spot-data-access/tasks/task-01.md", "source_location": "L21", "weight": 1.0}, {"source": "tasks_task_01_task_01_\u5199_data_raw_shanxi_readme_md_\u6570\u636e\u8d44\u4ea7\u8bf4\u660e", "target": "tasks_task_01_\u5b9e\u73b0\u8981\u6c42", "relation": "contains", "confidence": "EXTRACTED", "source_file": ".sillyspec/changes/archive/2026-06-23-2026-06-22-shanxi-spot-data-access/tasks/task-01.md", "source_location": "L26", "weight": 1.0}, {"source": "tasks_task_01_task_01_\u5199_data_raw_shanxi_readme_md_\u6570\u636e\u8d44\u4ea7\u8bf4\u660e", "target": "tasks_task_01_\u8986\u76d6\u6765\u6e90\u539f\u6587_\u4f9b\u53c2\u8003_execute_\u5b50\u4ee3\u7406\u65e0\u9700\u518d\u7ffb_design_decisions", "relation": "contains", "confidence": "EXTRACTED", "source_file": ".sillyspec/changes/archive/2026-06-23-2026-06-22-shanxi-spot-data-access/tasks/task-01.md", "source_location": "L39", "weight": 1.0}, {"source": "tasks_task_01_\u8986\u76d6\u6765\u6e90\u539f\u6587_\u4f9b\u53c2\u8003_execute_\u5b50\u4ee3\u7406\u65e0\u9700\u518d\u7ffb_design_decisions", "target": "tasks_task_01_\u51b3\u7b56_d_002_v1_record1_record2_\u91cd\u547d\u540d", "relation": "contains", "confidence": "EXTRACTED", "source_file": ".sillyspec/changes/archive/2026-06-23-2026-06-22-shanxi-spot-data-access/tasks/task-01.md", "source_location": "L41", "weight": 1.0}, {"source": "tasks_task_01_\u8986\u76d6\u6765\u6e90\u539f\u6587_\u4f9b\u53c2\u8003_execute_\u5b50\u4ee3\u7406\u65e0\u9700\u518d\u7ffb_design_decisions", "target": "tasks_task_01_\u51b3\u7b56_d_003_v1_rqrecord_ssrecord_\u91cd\u547d\u540d_load_mw_\u6620\u5c04", "relation": "contains", "confidence": "EXTRACTED", "source_file": ".sillyspec/changes/archive/2026-06-23-2026-06-22-shanxi-spot-data-access/tasks/task-01.md", "source_location": "L45", "weight": 1.0}, {"source": "tasks_task_01_\u8986\u76d6\u6765\u6e90\u539f\u6587_\u4f9b\u53c2\u8003_execute_\u5b50\u4ee3\u7406\u65e0\u9700\u518d\u7ffb_design_decisions", "target": "tasks_task_01_\u51b3\u7b56_d_006_v1_\u4ec5_3_api_\u63a5\u5165_\u5176\u4f59\u5f52\u6863", "relation": "contains", "confidence": "EXTRACTED", "source_file": ".sillyspec/changes/archive/2026-06-23-2026-06-22-shanxi-spot-data-access/tasks/task-01.md", "source_location": "L49", "weight": 1.0}, {"source": "tasks_task_01_task_01_\u5199_data_raw_shanxi_readme_md_\u6570\u636e\u8d44\u4ea7\u8bf4\u660e", "target": "tasks_task_01_\u63a5\u53e3\u5b9a\u4e49_\u4ee3\u7801\u7c7b\u4efb\u52a1\u5fc5\u586b_task_01_readme_\u7c7b\u586b\u5b57\u6bb5\u8868", "relation": "contains", "confidence": "EXTRACTED", "source_file": ".sillyspec/changes/archive/2026-06-23-2026-06-22-shanxi-spot-data-access/tasks/task-01.md", "source_location": "L53", "weight": 1.0}, {"source": "tasks_task_01_\u63a5\u53e3\u5b9a\u4e49_\u4ee3\u7801\u7c7b\u4efb\u52a1\u5fc5\u586b_task_01_readme_\u7c7b\u586b\u5b57\u6bb5\u8868", "target": "tasks_task_01_\u6587\u6863\u7ed3\u6784_markdown_\u6807\u9898\u5c42\u7ea7", "relation": "contains", "confidence": "EXTRACTED", "source_file": ".sillyspec/changes/archive/2026-06-23-2026-06-22-shanxi-spot-data-access/tasks/task-01.md", "source_location": "L55", "weight": 1.0}, {"source": "tasks_task_01_\u63a5\u53e3\u5b9a\u4e49_\u4ee3\u7801\u7c7b\u4efb\u52a1\u5fc5\u586b_task_01_readme_\u7c7b\u586b\u5b57\u6bb5\u8868", "target": "tasks_task_01_\u7b2c_2_\u8282_api_\u63a5\u5165\u6e05\u5355\u8868_\u5fc5\u987b\u5b8c\u6574_8_\u884c_11_\u884c\u975e\u6838\u5fc3\u5f52\u6863\u8868", "relation": "contains", "confidence": "EXTRACTED", "source_file": ".sillyspec/changes/archive/2026-06-23-2026-06-22-shanxi-spot-data-access/tasks/task-01.md", "source_location": "L79", "weight": 1.0}, {"source": "tasks_task_01_\u63a5\u53e3\u5b9a\u4e49_\u4ee3\u7801\u7c7b\u4efb\u52a1\u5fc5\u586b_task_01_readme_\u7c7b\u586b\u5b57\u6bb5\u8868", "target": "tasks_task_01_\u7b2c_3_\u8282_\u5b57\u6bb5\u6620\u5c04\u8be6\u8868_3_\u5f20\u5b50\u8868", "relation": "contains", "confidence": "EXTRACTED", "source_file": ".sillyspec/changes/archive/2026-06-23-2026-06-22-shanxi-spot-data-access/tasks/task-01.md", "source_location": "L94", "weight": 1.0}, {"source": "tasks_task_01_\u7b2c_3_\u8282_\u5b57\u6bb5\u6620\u5c04\u8be6\u8868_3_\u5f20\u5b50\u8868", "target": "tasks_task_01_3_1_spot_da", "relation": "contains", "confidence": "EXTRACTED", "source_file": ".sillyspec/changes/archive/2026-06-23-2026-06-22-shanxi-spot-data-access/tasks/task-01.md", "source_location": "L96", "weight": 1.0}, {"source": "tasks_task_01_\u7b2c_3_\u8282_\u5b57\u6bb5\u6620\u5c04\u8be6\u8868_3_\u5f20\u5b50\u8868", "target": "tasks_task_01_3_2_spot_rt", "relation": "contains", "confidence": "EXTRACTED", "source_file": ".sillyspec/changes/archive/2026-06-23-2026-06-22-shanxi-spot-data-access/tasks/task-01.md", "source_location": "L108", "weight": 1.0}, {"source": "tasks_task_01_\u7b2c_3_\u8282_\u5b57\u6bb5\u6620\u5c04\u8be6\u8868_3_\u5f20\u5b50\u8868", "target": "tasks_task_01_3_3_month_settle", "relation": "contains", "confidence": "EXTRACTED", "source_file": ".sillyspec/changes/archive/2026-06-23-2026-06-22-shanxi-spot-data-access/tasks/task-01.md", "source_location": "L118", "weight": 1.0}, {"source": "tasks_task_01_task_01_\u5199_data_raw_shanxi_readme_md_\u6570\u636e\u8d44\u4ea7\u8bf4\u660e", "target": "tasks_task_01_\u8fb9\u754c\u5904\u7406_\u81f3\u5c11_5_\u6761", "relation": "contains", "confidence": "EXTRACTED", "source_file": ".sillyspec/changes/archive/2026-06-23-2026-06-22-shanxi-spot-data-access/tasks/task-01.md", "source_location": "L129", "weight": 1.0}, {"source": "tasks_task_01_task_01_\u5199_data_raw_shanxi_readme_md_\u6570\u636e\u8d44\u4ea7\u8bf4\u660e", "target": "tasks_task_01_\u975e\u76ee\u6807_\u672c\u4efb\u52a1\u4e0d\u505a\u7684\u4e8b", "relation": "contains", "confidence": "EXTRACTED", "source_file": ".sillyspec/changes/archive/2026-06-23-2026-06-22-shanxi-spot-data-access/tasks/task-01.md", "source_location": "L139", "weight": 1.0}, {"source": "tasks_task_01_task_01_\u5199_data_raw_shanxi_readme_md_\u6570\u636e\u8d44\u4ea7\u8bf4\u660e", "target": "tasks_task_01_\u53c2\u8003", "relation": "contains", "confidence": "EXTRACTED", "source_file": ".sillyspec/changes/archive/2026-06-23-2026-06-22-shanxi-spot-data-access/tasks/task-01.md", "source_location": "L149", "weight": 1.0}, {"source": "tasks_task_01_task_01_\u5199_data_raw_shanxi_readme_md_\u6570\u636e\u8d44\u4ea7\u8bf4\u660e", "target": "tasks_task_01_tdd_\u6b65\u9aa4_\u4ee3\u7801\u7c7b\u4efb\u52a1_\u6587\u6863\u7c7b\u4efb\u52a1\u8df3\u8fc7", "relation": "contains", "confidence": "EXTRACTED", "source_file": ".sillyspec/changes/archive/2026-06-23-2026-06-22-shanxi-spot-data-access/tasks/task-01.md", "source_location": "L161", "weight": 1.0}, {"source": "tasks_task_01_task_01_\u5199_data_raw_shanxi_readme_md_\u6570\u636e\u8d44\u4ea7\u8bf4\u660e", "target": "tasks_task_01_\u9a8c\u6536\u6807\u51c6", "relation": "contains", "confidence": "EXTRACTED", "source_file": ".sillyspec/changes/archive/2026-06-23-2026-06-22-shanxi-spot-data-access/tasks/task-01.md", "source_location": "L173", "weight": 1.0}], "input_tokens": 0, "output_tokens": 0}